exeqpdal/__init__.py
exeqpdal/exceptions.py
exeqpdal/py.typed
exeqpdal/apps/__init__.py
exeqpdal/apps/info.py
exeqpdal/apps/pipeline_apps.py
exeqpdal/apps/translate.py
exeqpdal/core/__init__.py
exeqpdal/core/config.py
exeqpdal/core/executor.py
exeqpdal/core/pipeline.py
exeqpdal/stages/__init__.py
exeqpdal/stages/base.py
exeqpdal/stages/filters.py
exeqpdal/stages/readers.py
exeqpdal/stages/writers.py
exeqpdal/types/__init__.py
exeqpdal/types/dimensions.py
exeqpdal-0.1.0a5.dist-info/METADATA
exeqpdal-0.1.0a5.dist-info/WHEEL
exeqpdal-0.1.0a5.dist-info/licenses/LICENSE
exeqpdal-0.1.0a5.dist-info/RECORD
