Metadata-Version: 2.4
Name: exeqpdal
Version: 0.1.0a5
Summary: Python API for executing PDAL CLI commands with native syntax support
Project-URL: Homepage, https://github.com/elgorrion/exeqpdal
Project-URL: Documentation, https://github.com/elgorrion/exeqpdal#readme
Project-URL: Repository, https://github.com/elgorrion/exeqpdal
Project-URL: Bug Tracker, https://github.com/elgorrion/exeqpdal/issues
Project-URL: Changelog, https://github.com/elgorrion/exeqpdal/blob/main/CHANGELOG.md
Project-URL: Source Code, https://github.com/elgorrion/exeqpdal
Author-email: ElGorrion <elgorrion.eu@gmail.com>
License: MIT
License-File: LICENSE
Keywords: geospatial,lidar,pdal,pointcloud,qgis
Classifier: Development Status :: 3 - Alpha
Classifier: Intended Audience :: Developers
Classifier: Intended Audience :: Science/Research
Classifier: License :: OSI Approved :: MIT License
Classifier: Natural Language :: English
Classifier: Operating System :: OS Independent
Classifier: Programming Language :: Python :: 3
Classifier: Programming Language :: Python :: 3.12
Classifier: Topic :: Scientific/Engineering :: GIS
Classifier: Topic :: Software Development :: Libraries :: Python Modules
Classifier: Typing :: Typed
Requires-Python: >=3.12
Requires-Dist: numpy>=1.26.4
Provides-Extra: dev
Requires-Dist: build>=1.3.0; extra == 'dev'
Requires-Dist: mypy>=1.18.2; extra == 'dev'
Requires-Dist: pytest-cov>=7.0.0; extra == 'dev'
Requires-Dist: pytest>=8.4.2; extra == 'dev'
Requires-Dist: ruff>=0.14.0; extra == 'dev'
Requires-Dist: twine>=6.2.0; extra == 'dev'
